dearpypixl/__init__.py
dearpypixl/__main__.py
dearpypixl/_errors.py
dearpypixl/_interface.py
dearpypixl/_mkstub.py
dearpypixl/_parsing.py
dearpypixl/_tools.py
dearpypixl/_typing.py
dearpypixl/api.py
dearpypixl/color.py
dearpypixl/color.pyi
dearpypixl/console.py
dearpypixl/constants.py
dearpypixl/events.py
dearpypixl/grid.py
dearpypixl/items.py
dearpypixl/items.pyi
dearpypixl/menu.py
dearpypixl/py.typed
dearpypixl/style.py
dearpypixl/style.pyi
dearpypixl/themes.py
dearpypixl/theming.py
dearpypixl/typing.py
dearpypixl-1.2.13.dist-info/LICENSE
dearpypixl-1.2.13.dist-info/METADATA
dearpypixl-1.2.13.dist-info/WHEEL
dearpypixl-1.2.13.dist-info/top_level.txt
dearpypixl-1.2.13.dist-info/RECORD
